my_kegg_app/__init__.py
my_kegg_app/__main__.py
my_kegg_app/bigg_ec_database.csv
my_kegg_app/kegg_reactions_detailed.tsv
my_kegg_app/keggid_bigg_db.csv
my_kegg_app/routes.py
my_kegg_app/static/script.js
my_kegg_app/static/style.css
my_kegg_app/templates/index.html
my_kegg_app-0.1.0.dist-info/METADATA
my_kegg_app-0.1.0.dist-info/WHEEL
my_kegg_app-0.1.0.dist-info/entry_points.txt
my_kegg_app-0.1.0.dist-info/top_level.txt
my_kegg_app-0.1.0.dist-info/RECORD
