Metadata-Version: 2.4
Name: my_kegg_app
Version: 0.1.0
Summary: KEGG Reactions and EC Finder Web App
Author: Your Name
Author-email: your.email@example.com
Requires-Python: >=3.7
Requires-Dist: Flask
Requires-Dist: pandas
Requires-Dist: requests
Requires-Dist: biopython
Dynamic: author
Dynamic: author-email
Dynamic: requires-dist
Dynamic: requires-python
Dynamic: summary
